jumpscale/clients/_bcdb/Dockerfile
jumpscale/clients/_bcdb/__init__.py
jumpscale/clients/_bcdb/auth.py
jumpscale/clients/_bcdb/client.py
jumpscale/clients/btc_alpha/__init__.py
jumpscale/clients/btc_alpha/btc_alpha.py
jumpscale/clients/currencylayer/__init__.py
jumpscale/clients/currencylayer/currencies.py
jumpscale/clients/currencylayer/currencylayer.py
jumpscale/clients/digitalocean/__init__.py
jumpscale/clients/digitalocean/digitalocean.py
jumpscale/clients/digitalocean/project.py
jumpscale/clients/gedis/__init__.py
jumpscale/clients/gedis/gedis.py
jumpscale/clients/github/__init__.py
jumpscale/clients/github/base.py
jumpscale/clients/github/github.py
jumpscale/clients/github/helper.py
jumpscale/clients/github/issue.py
jumpscale/clients/github/milestone.py
jumpscale/clients/github/repo.py
jumpscale/clients/gogs/__init__.py
jumpscale/clients/gogs/gogs.py
jumpscale/clients/kraken/__init__.py
jumpscale/clients/kraken/kraken.py
jumpscale/clients/liquid/__init__.py
jumpscale/clients/liquid/liquid.py
jumpscale/clients/mail/__init__.py
jumpscale/clients/mail/mail.py
jumpscale/clients/name/__init__.py
jumpscale/clients/name/name.py
jumpscale/clients/s3/__init__.py
jumpscale/clients/s3/s3.py
jumpscale/clients/sendgrid/__init__.py
jumpscale/clients/sendgrid/sendgrid.py
jumpscale/clients/stellar/__init__.py
jumpscale/clients/stellar/balance.py
jumpscale/clients/stellar/exceptions.py
jumpscale/clients/stellar/readme.md
jumpscale/clients/stellar/stellar.py
jumpscale/clients/stellar/transaction.py
jumpscale/clients/stellar/vesting.py
jumpscale/clients/stellar/wrapped.py
jumpscale/clients/syncthing/__init__.py
jumpscale/clients/syncthing/syncthing.py
jumpscale/clients/taiga/__init__.py
jumpscale/clients/taiga/models.py
jumpscale/clients/taiga/taiga.py
jumpscale/clients/taiga/template.html
jumpscale/clients/zerotier/__init__.py
jumpscale/clients/zerotier/zerotier.py
jumpscale/core/identity/__init__.py
jumpscale/data/countries/__init__.py
jumpscale/data/treemanager/__init__.py
js_sdk-12.0.0.dist-info/entry_points.txt
js_sdk-12.0.0.dist-info/LICENSE
js_sdk-12.0.0.dist-info/WHEEL
js_sdk-12.0.0.dist-info/METADATA
js_sdk-12.0.0.dist-info/RECORD
