Metadata-Version: 2.1
Name: js-sdk
Version: 12.0.0
Summary: SDK for threefold grid
License: Apache-2.0
Author: xmonader
Author-email: xmonader@gmail.com
Requires-Python: >=3.7,<4.0
Classifier: License :: OSI Approved :: Apache Software License
Classifier: Programming Language :: Python :: 3
Classifier: Programming Language :: Python :: 3.7
Classifier: Programming Language :: Python :: 3.8
Classifier: Programming Language :: Python :: 3.9
Classifier: Programming Language :: Python :: 3.10
Classifier: Programming Language :: Python :: 3.11
Requires-Dist: PyGithub (>=1.43,<2.0)
Requires-Dist: base58 (>=2.0.0,<3.0.0)
Requires-Dist: beaker (>=1.11.0,<2.0.0)
Requires-Dist: certbot-nginx (>=1.31.0,<2.0.0)
Requires-Dist: certifi (>=2019.6,<2020.0)
Requires-Dist: crontab (>=0.22.9,<0.23.0)
Requires-Dist: cryptocompare (>=0.6.4,<0.7.0)
Requires-Dist: cryptography (==3.3.2)
Requires-Dist: dnspython (>=1.16,<2.0)
Requires-Dist: gevent (>=21.12.0,<22.0.0)
Requires-Dist: greenlet (>=1.1.3,<2.0.0)
Requires-Dist: importlib-metadata (>=4.0.1,<5.0.0)
Requires-Dist: js-ng (==11.0b17)
Requires-Dist: minio (>=4.0,<5.0)
Requires-Dist: namecom (>=0.5.0,<0.6.0)
Requires-Dist: netaddr (>=0.7.19,<0.8.0)
Requires-Dist: protobuf (>=3.12.2,<4.0.0)
Requires-Dist: pycountry (>=19.8,<20.0)
Requires-Dist: pypng (>=0.0.20,<0.0.21)
Requires-Dist: pyqrcode (>=1.2.1,<2.0.0)
Requires-Dist: python-digitalocean (>=1.15.0,<2.0.0)
Requires-Dist: python-taiga (>=1.0.0,<2.0.0)
Requires-Dist: requests_unixsocket (>=0.2.0,<0.3.0)
Requires-Dist: sendgrid (>=6.0,<7.0)
Requires-Dist: stellar-sdk (>=8.1.0,<9.0.0)
